./.gitignore
./PKG-INFO
./README.md
./pyproject.toml
./uv.lock
./agntcy/dir_sdk/client/__init__.py
./agntcy/dir_sdk/client/client.py
./agntcy/dir_sdk/client/config.py
./agntcy/dir_sdk/client/test_client.py
./agntcy/dir_sdk/models/README.md
./agntcy/dir_sdk/models/__init__.py
./agntcy/dir_sdk/models/core_v1.py
./agntcy/dir_sdk/models/routing_v1.py
./agntcy/dir_sdk/models/search_v1.py
./agntcy/dir_sdk/models/sign_v1.py
./agntcy/dir_sdk/models/store_v1.py
dir_test_pkg-0.4.1.dist-info/METADATA
dir_test_pkg-0.4.1.dist-info/WHEEL
dir_test_pkg-0.4.1.dist-info/RECORD
