Metadata-Version: 2.4
Name: dir-test-pkg
Version: 0.4.1
Summary: Directory SDK
Requires-Python: >=3.10
Requires-Dist: agntcy-dir-grpc-python==1.75.1.1.20251007090412+102a9af80c74
Requires-Dist: spiffe-tls>=0.2.1
Requires-Dist: spiffe>=0.2.2
